{
  "id": 70,
  "title": "Solution",
  "category": "physical-science",
  "imageFile": "p32.jpg",
  "imagePath": "images/physical-science/p32.jpg",
  "gradeLevel": "fourth-grade",
  "content": "## 📸 Photo Description\n\nA person reaches out to touch a giant soap bubble that shows beautiful rainbow colors. The bubble is floating in the air above a playground, and you can see the thin, clear wall of the bubble with colorful stripes moving across its surface.\n\n## 🔬 Scientific Phenomena\n\nThis image demonstrates the **Anchoring Phenomenon** of thin-film interference in soap bubbles. The rainbow colors appear because when light hits the soap bubble's thin walls, some light bounces off the outer surface while other light travels through the soap film and bounces off the inner surface. These two light waves then combine, and depending on how they line up, they either strengthen certain colors or cancel them out, creating the swirling rainbow patterns we see.\n\n## 📚 Core Science Concepts\n\n1. **Light Behavior**: Light waves can reflect, refract, and interfere with each other when they encounter different materials and surfaces.\n\n2. **Wave Properties**: Light travels in waves, and when waves meet, they can add together or cancel each other out, creating different effects.\n\n3. **Material Properties**: Soap bubbles have very thin walls made of water and soap molecules that create a film thin enough to interact with light waves.\n\n4. **Surface Tension**: The soap film maintains its bubble shape due to surface tension, which pulls the molecules together to create the smallest possible surface area.\n\n<pedagogical-tip>Have students predict what will happen to the colors if they blow bubbles of different sizes, then test their predictions. This helps develop scientific reasoning skills.</pedagogical-tip>\n\n<udl-suggestions>Provide multiple ways for students to observe bubbles - through direct observation, slow-motion videos, and magnifying glasses to accommodate different visual processing needs and learning preferences.</udl-suggestions>\n\n## 🔍 Zoom In / Zoom Out Concepts\n\n1. **Zoom In:** At the molecular level, soap molecules arrange themselves in a thin layer with water molecules trapped between them. The thickness of this film (only a few hundred nanometers) is what determines which colors of light interfere constructively or destructively.\n\n2. **Zoom Out:** This same light interference phenomenon occurs in nature on larger scales - in oil slicks on water, peacock feathers, butterfly wings, and even in the aurora borealis when solar particles interact with Earth's atmosphere.\n\n## 🤔 Potential Student Misconceptions\n\n1. **Misconception:** The colors are painted on the bubble or come from the soap.\n   **Clarification:** The colors come from white light being separated when light waves interfere with each other at the bubble's surface.\n\n2. **Misconception:** All bubbles should look the same.\n   **Clarification:** Bubble colors change constantly because the soap film thickness varies and changes due to gravity and evaporation.\n\n3. **Misconception:** You need special soap to make colorful bubbles.\n   **Clarification:** Any soap bubble will show colors when light hits it at the right angle, though some soap solutions work better than others.\n\n## 🎓 NGSS Connections\n\n- **Performance Expectation:** 4-PS4-2 - Develop a model to describe that light reflecting from objects and entering the eye allows objects to be seen\n- **Disciplinary Core Ideas:** [[NGSS:DCI:PS4.B]] - Electromagnetic Radiation\n- **Crosscutting Concepts:** [[NGSS:CCC:Patterns]] and [[NGSS:CCC:Cause and Effect]]\n- **Science and Engineering Practices:** Developing and Using Models\n\n## 💬 Discussion Questions\n\n1. What do you think would happen to the colors if we made the bubble bigger or smaller? (Bloom's: Predict | DOK: 2)\n\n2. Why do you see different colors in different parts of the same bubble? (Bloom's: Analyze | DOK: 2)\n\n3. How is a soap bubble similar to a rainbow, and how is it different? (Bloom's: Compare | DOK: 3)\n\n4. What other objects have you seen that show rainbow colors like this bubble? (Bloom's: Apply | DOK: 2)\n\n## 📖 Science Vocabulary\n\n* **Interference:** When two or more light waves meet and combine to make colors brighter or dimmer.\n* **Reflection:** When light bounces off the surface of an object.\n* **Film:** A very thin layer of material, like the wall of a soap bubble.\n* **Surface tension:** The force that holds the molecules in a liquid together at the surface.\n* **Wavelength:** The distance between one wave peak and the next wave peak in light.\n\n## 🔗 Cross-Curricular Ideas\n\n1. **Math - Measurement and Patterns**: Have students measure the diameter of bubbles they create and record how long the colors last before the bubble pops. They can create bar graphs or line plots to show their data and look for patterns in bubble size and lifespan.\n\n2. **ELA - Descriptive Writing**: Ask students to write detailed descriptions of the colors and patterns they observe in soap bubbles using sensory language. They could write poems or short stories from the perspective of a bubble floating through the air.\n\n3. **Art - Color Mixing and Light**: Create artwork inspired by soap bubbles using watercolors, pastels, or digital tools. Students can explore how colors blend and transition like they do in bubbles, and discuss how artists use light and shadow to create depth and movement in their work.\n\n4. **Social Studies - History of Discovery**: Research the history of how scientists discovered and explained the rainbow colors in soap bubbles. Students can learn about famous scientists like Isaac Newton who studied light and color, and create timelines of important discoveries in optics.\n\n## 🚀 STEM Career Connection\n\n1. **Optical Engineer**: Optical engineers design and build tools that use light, like cameras, telescopes, and microscopes. They study how light behaves (like in soap bubbles!) to create instruments that help us see things better. Some optical engineers work on special eyeglasses or medical imaging equipment. **Average Annual Salary: $75,000 - $90,000**\n\n2. **Materials Scientist**: Materials scientists study the properties of different substances to understand how they work and create new materials. A materials scientist might investigate why soap bubbles form rainbow colors, or develop new types of soap or coatings for products. **Average Annual Salary: $65,000 - $85,000**\n\n3. **Physicist**: Physicists study how light, energy, and matter work. They conduct experiments to understand phenomena like light interference and wave behavior. Some physicists work in laboratories discovering new science, while others apply their knowledge to create new technologies. **Average Annual Salary: $70,000 - $95,000**\n\n## 📚 External Resources\n\n**Children's Books:**\n- Bubbles, Bubbles Everywhere by Melvin Berger\n- Pop! A Book About Bubbles by Kimberly Brubaker Bradley\n- The Magic School Bus: Light and Sound by Joanna Cole",
  "generatedAt": "2026-02-04T17:37:45.180Z"
}