{
  "id": 1,
  "title": "Seedling",
  "category": "life-science",
  "imageFile": "100_1681.jpeg",
  "imagePath": "images/life-science/100_1681.jpeg",
  "gradeLevel": "fourth-grade",
  "content": "## 📸 Photo Description\n\nA small plant with green leaves is growing from a clear plastic bottle that has been cut and filled with dark soil. The bottle is sitting on a windowsill with sunlight coming through. This shows how people can reuse materials to create a simple planter for growing plants.\n\n## 🔬 Scientific Phenomena\n\nThis image demonstrates the **Anchoring Phenomenon** of plant growth and germination in an upcycled container. The plant is exhibiting positive phototropism (growing toward the light source from the window) and has successfully established itself in the makeshift planter. The phenomenon occurs because plants need specific environmental conditions - light, water, nutrients from soil, and carbon dioxide - to carry out photosynthesis and cellular respiration for growth. The clear bottle allows us to observe the root system and soil environment that supports the plant's development.\n\n## 📚 Core Science Concepts\n\n1. **Plant Life Cycles and Growth Requirements** - Plants need sunlight, water, air, and nutrients from soil to survive and grow through their life cycle stages.\n\n2. **Phototropism and Plant Responses** - Plants respond to their environment by growing toward light sources to maximize photosynthesis.\n\n3. **Recycling and Environmental Stewardship** - Humans can reduce waste by repurposing materials like plastic bottles for new uses like planters.\n\n4. **Structure and Function Relationships** - The plant's leaves are positioned to capture maximum sunlight, while roots (hidden in soil) absorb water and nutrients.\n\n<pedagogical-tip>Use this image to launch a classroom investigation where students create their own bottle planters and track plant growth over time. This hands-on approach helps students make concrete observations about abstract biological processes.</pedagogical-tip>\n\n<udl-suggestions>Provide multiple ways for students to document plant observations - through drawings, photos, measurements, or verbal recordings - to accommodate different learning preferences and abilities.</udl-suggestions>\n\n## 🔍 Zoom In / Zoom Out Concepts\n\n1. **Zoom In:** At the cellular level, chloroplasts in the plant's leaves are capturing light energy and converting carbon dioxide and water into glucose through photosynthesis, while root cells are actively absorbing water and dissolved minerals from the soil.\n\n2. **Zoom Out:** This small container garden connects to larger environmental systems - the plant helps clean air by absorbing CO₂, the recycled bottle reduces landfill waste, and successful container gardening can contribute to urban food systems and biodiversity.\n\n## 🤔 Potential Student Misconceptions\n\n1. **Misconception:** Plants get their food from the soil like animals eat food.\n   **Clarification:** Plants make their own food through photosynthesis using sunlight, water, and carbon dioxide. Soil provides water and nutrients, but not food.\n\n2. **Misconception:** Plants don't need air to survive.\n   **Clarification:** Plants need carbon dioxide from air for photosynthesis and oxygen for cellular respiration, just like animals.\n\n3. **Misconception:** Any container will work equally well for growing plants.\n   **Clarification:** Containers need drainage holes and appropriate size for root growth. This bottle setup works but may need modifications for long-term plant health.\n\n## 🎓 NGSS Connections\n\n- **Performance Expectation:** 5-LS1-1 - Support an argument that plants get the materials they need for growth chiefly from air and water\n- **Disciplinary Core Ideas:** [[NGSS:DCI:5-LS1.C]] - Organization for Matter and Energy Flow in Organisms\n- **Disciplinary Core Ideas:** [[NGSS:DCI:K-ESS3.A]] - Natural Resources  \n- **Crosscutting Concepts:** [[NGSS:CCC:Systems and System Models]]\n- **Crosscutting Concepts:** [[NGSS:CCC:Structure and Function]]\n\n## 💬 Discussion Questions\n\n1. What evidence can you observe that shows this plant is healthy and growing well? (Bloom's: Analyze | DOK: 2)\n\n2. How might this plant's growth change if we moved it to a dark closet for a week? (Bloom's: Predict/Hypothesize | DOK: 3)\n\n3. What are the advantages and disadvantages of using a plastic bottle instead of a clay pot for growing plants? (Bloom's: Evaluate | DOK: 3)\n\n4. How does reusing this bottle for a planter help both the plant and the environment? (Bloom's: Synthesize | DOK: 2)\n\n## 📖 Science Vocabulary\n\n* **Photosynthesis:** The process plants use to make food from sunlight, water, and carbon dioxide\n* **Germination:** When a seed begins to grow into a new plant\n* **Phototropism:** The way plants grow toward light sources\n* **Upcycling:** Reusing old materials to create something new and useful\n* **Life cycle:** The stages a living thing goes through as it grows and develops\n* **Nutrients:** Important substances from soil that help plants stay healthy\n\n## 🔗 Cross-Curricular Ideas\n\n1. **Math Connection - Measurement and Growth Tracking:** Students can measure their bottle plants weekly using rulers and create line graphs to show plant height over time. This reinforces measurement skills and data representation while connecting to the science of plant growth rates.\n\n2. **ELA Connection - Informative Writing:** Have students write step-by-step instructions for creating a bottle planter, or write persuasive letters to their families explaining why upcycling is important. This builds procedural and persuasive writing skills while reinforcing scientific vocabulary.\n\n3. **Art Connection - Environmental Awareness Posters:** Students can create colorful posters showing ways to reduce, reuse, and recycle materials. They could illustrate different items that can be upcycled into planters, combining art skills with environmental messaging.\n\n4. **Social Studies Connection - Community Gardens:** Research local community gardens or urban farming projects in your area. Discuss how growing plants in containers helps communities with limited space grow their own food, connecting to civic responsibility and sustainable living.\n\n## 🚀 STEM Career Connection\n\n1. **Botanist** - A botanist is a scientist who studies plants and how they grow. Botanists work to understand plant diseases, develop new crop varieties, and help protect endangered plants. They might work in laboratories, greenhouses, or outdoors in nature. Some botanists help create better gardens and farms to grow food for communities. **Average Annual Salary: $63,000**\n\n2. **Environmental Engineer** - Environmental engineers design systems to help protect our planet. They work on projects like creating recycling programs, managing waste, and designing sustainable spaces where plants and people can thrive together. Some environmental engineers help design green roofs or community gardens in cities. **Average Annual Salary: $96,000**\n\n3. **Horticulturist** - A horticulturist is an expert in growing plants like fruits, vegetables, flowers, and ornamental plants. They work in nurseries, botanical gardens, farms, and research facilities to help plants grow healthily and develop better plant varieties. Horticulturists use their knowledge to teach people how to garden successfully. **Average Annual Salary: $52,000**\n\n## 📚 External Resources\n\n**Children's Books:**\n- From Seed to Plant by Gail Gibbons\n- The Reason for a Flower by Ruth Heller\n- A Seed Is Sleepy by Dianna Hutts Aston",
  "generatedAt": "2026-02-04T01:03:10.326Z"
}