{
  "id": 0,
  "title": "Alligator_predator",
  "category": "life-science",
  "imageFile": "alligator_predator.jpg",
  "imagePath": "images/life-science/alligator_predator.jpg",
  "gradeLevel": "Kindergarten",
  "content": "# Kindergarten Science Lesson: Alligators in Their Habitat\n\n## 📸 Photo Description\nThis photo shows an alligator resting in shallow, murky water surrounded by plants and mud. The alligator's bumpy skin helps it blend in with its wet environment. You can see small plants growing in the water around the alligator.\n\n## 🔬 Scientific Phenomena\n**Anchoring Phenomenon:** *An alligator is camouflaged in its swamp habitat.*\n\n**Why this happens:** Alligators have bumpy, dark-colored skin that looks very similar to mud, logs, and rocks in swamps and wetlands. This camouflage is an adaptation that helps alligators hide from other animals and sneak up on prey without being noticed. The murky, greenish water of their habitat also helps conceal them. This is a survival strategy—alligators blend in with their environment so well that other animals cannot easily see them.\n\n## 📚 Core Science Concepts\n\n1. **Habitats and Environments:** Alligators live in specific places called wetlands or swamps where there is shallow water, mud, and plants. Different animals live in different habitats.\n\n2. **Camouflage (Adaptation):** Alligators have special features—like bumpy, dark skin—that help them blend into their surroundings so predators cannot see them easily and so they can hunt for food.\n\n3. **Living Things and Their Needs:** Alligators need water, food, and shelter to survive. Swamps provide all these things.\n\n4. **Predators and Prey:** Alligators are predators that hunt other animals for food in their wetland habitat.\n\n<pedagogical-tip>\nWhen teaching about camouflage to Kindergarteners, use concrete, visible examples first. Start by showing the photo and asking children to find the alligator—this tactile \"search\" activity helps them understand the concept of hiding through color and pattern matching before moving to abstract definitions.\n</pedagogical-tip>\n\n<udl-suggestions>\nProvide multiple means of representation: Show the image on a large screen, pass around pictures of alligators, and provide tactile models or stuffed animals. Offer options for engagement by allowing students to draw, act out the alligator hiding, or use manipulatives to create a swamp habitat. This supports kinesthetic and visual learners while building language skills across all ability levels.\n</udl-suggestions>\n\n## 🎓 NGSS Connections\n\n**Performance Expectation (K-LS1-1):** Use observations to describe patterns of what plants and animals (including humans) need to survive.\n\n**Relevant Disciplinary Core Ideas:**\n- [[NGSS:DCI:K-LS1.A]] - All organisms have basic needs, such as water, material to build structures, and food. Additionally, plants need light and animals need food; plants get their material for growth chiefly from air and water.\n- [[NGSS:DCI:LS2.D]] - There are many different kinds of living things in any area, and they exist in different places on land and in water.\n\n**Crosscutting Concepts:**\n- [[NGSS:CCC:Patterns]] - Patterns in the natural and human-designed world can be observed, used to describe phenomena, and used as evidence.\n- [[NGSS:CCC:Structure-and-Function]] - The shape and stability of structures of natural and designed objects are related to their function(s).\n\n## 💬 Discussion Questions\n\n1. **Where does the alligator live, and what do you see in this picture that it needs?** (Bloom's: Understand | DOK: 1)\n\n2. **Why do you think the alligator's bumpy, dark skin helps it survive in the swamp?** (Bloom's: Analyze | DOK: 2)\n\n3. **If an alligator lived in a bright, sandy desert instead of a muddy swamp, how might its skin color be different to help it hide?** (Bloom's: Evaluate | DOK: 3)\n\n4. **What other animals might live in the same swamp with the alligator, and what would they need to stay alive?** (Bloom's: Create | DOK: 3)\n\n## 📖 Vocabulary\n\n* **Alligator:** A large reptile with tough, bumpy skin that lives in water and wet places.\n* **Habitat:** The place where an animal lives that has everything it needs to survive, like food and water.\n* **Camouflage:** Colors, patterns, or shapes on an animal's body that help it blend in and hide from other animals.\n* **Swamp:** A wet, muddy place with shallow water, mud, and lots of plants where alligators live.\n* **Predator:** An animal that hunts and eats other animals for food.\n* **Adaptation:** A special feature or behavior that helps an animal survive in its habitat.\n\n## 🌡️ Extension Activities\n\n1. **Camouflage Hide-and-Seek Game:** Hide pictures of animals (alligators, frogs, snakes, turtles) in a \"swamp\" made from a large tray filled with mud-colored paper, green tissue paper, and brown fabric. Have children search for hidden animals and discuss why some are harder to find than others based on their colors.\n\n2. **Create Your Own Swamp Habitat:** Provide a shallow bin with water, mud, green plants (real or craft materials), and toy alligators. Have students build and observe the habitat, discussing what the alligator needs and why it can hide so well in this environment.\n\n3. **Alligator Skin Texture Rubbing:** Provide textured materials (bumpy foam, ridged cardboard, rough sandpaper) and have children make rubbings to feel what alligator skin might feel like. Compare textures and discuss how bumpy, rough skin might help protect and camouflage the alligator.\n\n## 🔍 Zoom In / Zoom Out Concepts\n\n**Zoom In: Alligator Skin Cells**\nIf we could look at alligator skin under a super powerful magnifying glass, we would see tiny bumps called *scales* made of special material called *keratin* (the same stuff your fingernails are made of!). These scales overlap like roof tiles and have ridges and bumps. Under each scale are layers of cells that help protect the alligator's body from getting hurt and from drying out. The dark color in these cells helps the alligator blend in. This tiny-level camouflage works because the scales reflect light in a way that makes the alligator look like mud and rocks.\n\n**Zoom Out: The Wetland Ecosystem**\nThe swamp is part of a much larger system called an *ecosystem*. The alligator is just one animal in this ecosystem. The water, plants, fish, frogs, birds, insects, and mud all work together. The alligator eats fish and smaller animals (it's a predator), and when the alligator dies, its body feeds the soil and other decomposers. The plants need the water and nutrients. Everything is connected! The entire wetland ecosystem depends on the right amount of water, sunlight, and nutrients to keep all the living things alive. Alligators are an important part of keeping this ecosystem healthy and balanced.\n\n## 🤔 Potential Student Misconceptions\n\n**Misconception 1: \"Alligators change their skin color to hide, like a chameleon.\"**\n*Clarification:* Alligators cannot change their skin color. Their bumpy, dark skin is always the same color. The reason they blend in with their swamp is because their skin color and bumpy texture naturally look like mud, logs, and rocks. It's not a superpower—it's just lucky that they were born looking like their home! This is called *camouflage*, and it works because their color and pattern match their environment.\n\n**Misconception 2: \"Alligators are dinosaurs, and they are extinct like T-Rex.\"**\n*Clarification:* Alligators are reptiles, not dinosaurs. While alligators have been around for a very long time (even before some dinosaurs!), they are still alive today. Many alligators live in swamps and wetlands in places like Florida. Dinosaurs went extinct millions of years ago, but alligators adapted and survived!\n\n**Misconception 3: \"The alligator hides because it is scared of other animals.\"**\n*Clarification:* Alligators hide using camouflage, but not because they are scared. Alligators are *predators*, which means they hunt other animals for food. They hide so that fish, frogs, and other prey animals cannot see them coming. This helps the alligator catch its dinner! Camouflage is a hunting trick, not a scared trick.\n\n## 🔗 Cross-Curricular Ideas\n\n**Math Connection: Counting and Patterns**\nHave students count the bumps and ridges they see on the alligator in the photo (or on a model/toy alligator). Create a simple pattern using bumpy and smooth textures (bumpy-smooth-bumpy-smooth) to help students understand patterns. Use a ten-frame to count alligator teeth, scales, or spots. This builds early numeracy and pattern recognition skills.\n\n**ELA Connection: Descriptive Language and Storytelling**\nRead aloud a Kindergarten-level book about alligators, then have students use descriptive words (bumpy, dark, muddy, wet, slimy, long) to describe what they see in the photo. Have them dictate or draw a story about \"A Day in the Life of an Alligator\" hiding in the swamp. Create a class word wall with alligator habitat vocabulary and use it for shared writing activities.\n\n**Art Connection: Camouflage Collage**\nProvide students with torn pieces of brown, green, and gray paper along with textured materials (corrugated cardboard, sandpaper, fabric scraps). Have them create a mixed-media collage of an alligator hiding in a swamp, layering materials to show how the alligator blends in. Discuss how artists use colors and textures to hide or show things in their artwork, just like nature camouflages the alligator.\n\n**Social Studies Connection: Animal Homes Around the World**\nExpand the habitat concept by exploring where different animals live. Compare the alligator's swamp habitat to the homes of other animals (bears in forests, penguins in ice, camels in deserts). Discuss how each animal's home provides what it needs. Use a simple world map to show where alligators live (Florida, Louisiana, other warm, wet places) and compare to students' own homes and communities.\n\n## 🚀 STEM Career Connection\n\n**Wildlife Biologist / Alligator Researcher**\nWildlife biologists study animals like alligators in their natural homes. They watch alligators, count them, learn what they eat, and study how they survive. Some wildlife biologists work in swamps and wetlands to protect alligators and make sure they stay healthy. They use cameras, boats, and tools to observe and learn about these amazing reptiles. This job helps us understand nature better and protect animals!\n*Average Annual Salary: $65,000 USD*\n\n**Zookeeper / Wildlife Educator**\nZookeepers take care of alligators and other animals in zoos and wildlife centers. They feed the alligators, clean their habitats, and teach visitors (like you!) about how alligators live and why they are important. Zookeepers make sure the animals are healthy and happy. They love working with animals and helping people learn about nature!\n*Average Annual Salary: $32,000 USD*\n\n**Wetland Ecologist / Environmental Scientist**\nWetland ecologists study swamps and wetlands to understand how all the plants and animals work together. They protect these special habitats so that alligators and other creatures have safe homes. These scientists work to keep the water clean, protect the plants, and make sure the ecosystem stays healthy and balanced. Their work helps save nature!\n*Average Annual Salary: $68,000 USD*\n\n## 📚 External Resources\n\n**Children's Books:**\n- *Gators* by Kate Boehm Jerome (National Geographic Little Kids)\n- *See the Alligator* by Loretta Holland (Rookie Readers)\n- *Alligators and Crocodiles* by Seymour Simon",
  "generatedAt": "2026-02-06T03:33:29.096Z"
}