{
  "id": 9,
  "title": "Seed Germination",
  "category": "life-science",
  "imageFile": "IMG_9509,jpeg.jpg",
  "imagePath": "images/life-science/IMG_9509,jpeg.jpg",
  "gradeLevel": "third-grade",
  "content": "## 📸 Photo Description\n\nA small green plant with round leaves is growing up through old, dry plant pieces on the ground. The tiny plant looks fresh and healthy even though it is surrounded by brown, dead material. You can see the plant's green stem and several small leaves reaching toward the light.\n\n## 🔬 Scientific Phenomena\n\nThis image shows the **Anchoring Phenomenon** of plant germination and early growth in a natural environment. A seed has sprouted and is developing into a young seedling (called a germling) despite growing through decomposing organic matter. This is happening because the seed contained stored energy and nutrients needed for initial growth, and the surrounding decomposed material actually provides additional nutrients and helps retain moisture. The young plant is demonstrating its ability to push through obstacles to reach sunlight, which it needs for photosynthesis to continue growing.\n\n## 📚 Core Science Concepts\n\n1. **Seed Germination**: Seeds contain everything a new plant needs to start growing, including a tiny plant (embryo) and stored food energy.\n\n2. **Plant Life Cycle**: This seedling represents the early stage of a plant's life cycle, transitioning from seed to mature plant.\n\n3. **Plant Needs**: Plants require water, sunlight, air, and nutrients from soil to survive and grow.\n\n4. **Adaptation and Survival**: Plants have structures that help them survive in their environment, like strong stems that can push through debris.\n\n<pedagogical-tip>Have students act out being a seed germinating by starting curled up on the floor, then slowly \"growing\" upward while reaching for the \"sunlight.\" This kinesthetic activity helps them understand the process and remember the sequence.</pedagogical-tip>\n\n<udl-suggestions>Provide multiple ways for students to observe plant growth: real seedlings, time-lapse videos, and detailed photographs. Offer various recording methods like drawings, photos, or verbal descriptions to accommodate different learning preferences and abilities.</udl-suggestions>\n\n## 🔍 Zoom In / Zoom Out Concepts\n\n1. **Zoom In**: Inside the seed, cells are dividing rapidly to create new plant tissues. The root cells are growing downward following gravity, while shoot cells are growing upward toward light. Water is being absorbed into cells, making them expand and grow.\n\n2. **Zoom Out**: This single seedling is part of a larger ecosystem where decomposing plant matter enriches the soil for new plants. As this plant grows, it will produce oxygen, provide food for animals, and eventually create seeds to continue the cycle in the forest or grassland community.\n\n## 🤔 Potential Student Misconceptions\n\n1. **Misconception**: Plants get their food from soil.\n   **Reality**: Plants make their own food through photosynthesis using sunlight, water, and carbon dioxide. Soil provides nutrients and water, but not food.\n\n2. **Misconception**: Seeds need soil to grow.\n   **Reality**: Seeds can germinate in various materials as long as they have water, proper temperature, and air. The seed contains its own food supply for initial growth.\n\n3. **Misconception**: Dead plant material is harmful to new plants.\n   **Reality**: Decomposing plant matter provides valuable nutrients and helps create healthy soil for new plant growth.\n\n## 🎓 NGSS Connections\n\n- **Performance Expectation**: 3-LS1-1 - Develop models to describe that organisms have unique and diverse life cycles but all have in common birth, growth, reproduction, and death.\n- **Disciplinary Core Ideas**: [[NGSS:DCI:3-LS1.B]] - Growth and Development of Organisms\n- **Crosscutting Concepts**: [[NGSS:CCC:Patterns]] and [[NGSS:CCC:Systems and System Models]]\n\n## 💬 Discussion Questions\n\n1. What do you think this plant needed to grow through all that dead material? (Bloom's: Analyze | DOK: 2)\n\n2. How might this young plant change the environment around it as it continues to grow? (Bloom's: Evaluate | DOK: 3)\n\n3. What patterns do you notice between where plants grow and what surrounds them? (Bloom's: Analyze | DOK: 2)\n\n4. If you planted seeds in different materials, what do you predict would happen and why? (Bloom's: Create | DOK: 3)\n\n## 📖 Science Vocabulary\n\n* **Seedling**: A young plant that has just started growing from a seed\n* **Germination**: The process when a seed begins to grow into a new plant\n* **Decompose**: When dead plants and animals break down and become part of the soil\n* **Nutrients**: Substances that help living things grow and stay healthy\n* **Photosynthesis**: The process plants use to make food using sunlight, water, and air\n\n## 🔗 Cross-Curricular Ideas\n\n1. **Math - Measurement & Growth Tracking**: Have students plant seeds and measure seedling height weekly using non-standard units (paper clips, craft sticks) or standard units (centimeters). Create a simple bar graph or line plot to show how much the plant grows each week. This connects measurement, data collection, and graphing skills.\n\n2. **ELA - Sequencing & Narrative Writing**: Students can write or illustrate the sequence of events in a plant's life cycle using \"First, Next, Then, Finally\" sentence starters. They could also create a story from the perspective of a seed, describing its journey from germination through growth.\n\n3. **Art - Nature Collage & Observation Drawing**: Students can create detailed observational drawings of seedlings or make collages using actual plant materials (dried leaves, twigs, seeds). This develops fine motor skills and encourages close observation of natural details while creating beautiful artwork.\n\n4. **Social Studies - Community Gardens & Food Growth**: Connect to local gardens in the community. Discuss where food comes from and how plants are grown. Students could learn about farmers and gardeners as community helpers who grow plants to feed people.\n\n## 🚀 STEM Career Connection\n\n1. **Botanist** - A botanist is a scientist who studies plants. They learn about how plants grow, what they need to be healthy, and how plants help our environment. Botanists work in gardens, forests, and laboratories to discover new things about plants. They might help create better vegetables for farmers to grow or protect endangered plants. *Average Annual Salary: $65,000*\n\n2. **Farmer/Agricultural Scientist** - Farmers and agricultural scientists grow plants and crops that feed people and animals. They use science to figure out the best ways to plant seeds, water them, and help them grow strong and healthy. They might work outdoors in fields or in laboratories testing soil and seeds. *Average Annual Salary: $68,000*\n\n3. **Horticulturist** - A horticulturist is someone who grows plants, flowers, fruits, and vegetables in gardens, nurseries, and greenhouses. They know all about what different plants need to grow best and how to care for them. They might design beautiful gardens or help grow food for communities. *Average Annual Salary: $62,000*\n\n## 📚 External Resources\n\n**Children's Books:**\n- From Seed to Plant by Gail Gibbons\n- The Tiny Seed by Eric Carle\n- A Seed Is Sleepy by Dianna Hutts Aston",
  "generatedAt": "2026-02-04T01:35:39.305Z"
}