{
  "id": 0,
  "title": "Insect_characteristics",
  "category": "life-science",
  "imageFile": "insect_characteristics.jpg",
  "imagePath": "images/life-science/insect_characteristics.jpg",
  "gradeLevel": "Fourth Grade",
  "content": "# Fourth Grade Science Lesson Analysis: Insect Characteristics\n\n## 📸 Photo Description\nThis image shows a grasshopper sitting on a green leaf. The grasshopper has a green body with brown markings, long antennae (feelers) sticking out from its head, and powerful back legs. You can see its large eyes and the way its body is built for jumping and living on plants.\n\n## 🔬 Scientific Phenomena\n**Anchoring Phenomenon:** Why do grasshoppers have the body parts they do?\n\nGrasshoppers have specific body structures that help them survive in their environment. Their long, powerful back legs allow them to jump away from predators quickly. Their antennae help them sense their surroundings and find food. Their green color helps them blend in with plants, protecting them from animals that want to eat them. This is called **adaptation**—animals develop special features over many generations that help them survive and thrive in their habitat.\n\n## 📚 Core Science Concepts\n\n* **Insect Body Structure:** All insects have six legs, three body parts (head, thorax, and abdomen), and antennae. Grasshoppers are insects.\n\n* **Adaptations:** Grasshoppers have strong back legs for jumping, antennae for sensing, and green coloring to hide on plants. These features help them survive.\n\n* **Life Cycles:** Grasshoppers go through different stages of growth before becoming adults that can jump and reproduce.\n\n* **Habitats and Food Chains:** Grasshoppers live on plants and eat grass and leaves. They are food for birds, lizards, and other animals.\n\n<pedagogical-tip>\nWhen teaching about insect adaptations, use the strategy of \"structure meets function.\" Have students physically act out how each body part helps the grasshopper survive (e.g., pretend to jump with powerful legs, wave antennae to sense food). This kinesthetic approach helps fourth graders remember that body structures have specific jobs.\n</pedagogical-tip>\n\n<udl-suggestions>\nTo support diverse learners: (1) Provide labeled diagrams of grasshopper body parts for visual learners; (2) Allow students to handle preserved insects or use digital magnifying tools; (3) Offer a word bank of vocabulary terms; (4) Create a comparison chart showing how grasshopper legs differ from human legs to activate prior knowledge.\n</udl-suggestions>\n\n## 🎓 NGSS Connections\n\n**Performance Expectation:**\n4-LS1-1: Construct an argument that plants get the materials they need for growth chiefly from air and water.\n\n**Related Performance Expectation:**\n4-LS1-2: Use evidence to construct an explanation for how the variations in characteristics among individuals of the same species may provide advantages in surviving, finding mates, and reproducing.\n\n**Disciplinary Core Ideas:**\n* [[NGSS:DCI:4-LS1.A]] — Structure and Function\n* [[NGSS:DCI:4-LS1.D]] — Information Processing\n* [[NGSS:DCI:4-LS4.B]] — Natural Selection\n\n**Crosscutting Concepts:**\n* [[NGSS:CCC:Structure and Function]] — The shape and materials of natural and designed objects relate to common uses.\n* [[NGSS:CCC:Cause and Effect]] — Events that occur together with regularity might or might not have a causal relationship. Further investigation is needed to determine whether they are related.\n\n## 💬 Discussion Questions\n\n1. **What body parts does this grasshopper have that help it survive in its environment, and why do you think it needs each one?** (Bloom's: Analyze | DOK: 2)\n\n2. **How would a grasshopper's life be different if it didn't have strong back legs for jumping?** (Bloom's: Evaluate | DOK: 3)\n\n3. **Why do you think this grasshopper is green instead of red or blue?** (Bloom's: Infer | DOK: 2)\n\n4. **If grasshoppers lived in a rocky desert instead of a grassy field, what body changes might help them survive better over many generations?** (Bloom's: Create | DOK: 3)\n\n## 📖 Vocabulary\n\n* **Adaptation:** A body part or behavior that helps an animal survive in its environment.\n\n* **Antennae:** Long, thin feelers on an insect's head that help it sense things around it, like food and danger.\n\n* **Thorax:** The middle section of an insect's body where the legs and wings attach.\n\n* **Camouflage:** Coloring or pattern that helps an animal blend in with its surroundings so predators don't see it.\n\n* **Habitat:** The place where an animal or plant naturally lives and finds food, water, and shelter.\n\n## 🌡️ Extension Activities\n\n1. **Grasshopper Body Part Investigation:** Provide students with clear pictures or preserved specimens (from scientific supply companies). Have them use hand lenses to observe and sketch each body part. Create a labeled diagram together, and discuss what each part does. Students can then teach a partner about their observations.\n\n2. **Adaptation Design Challenge:** Show students pictures of different habitats (desert, forest, ice). Ask: \"If a grasshopper lived here instead of on grass, what would need to change?\" Have students draw an adapted grasshopper and explain how each change would help it survive in that new environment.\n\n3. **Insect Diversity Walk & Comparison Chart:** Take students on a nature walk (or show nature photos) to observe different insects. Create a comparison chart showing how grasshoppers are similar to and different from other insects like ants, beetles, or butterflies. This reinforces that insects share common features but have unique adaptations.\n\n## 🔍 Zoom In / Zoom Out Concepts\n\n**Zoom In: Cellular & Sensory Level**\nIf we could shrink down and look inside a grasshopper's antennae under a microscope, we would see thousands of tiny sensory cells. These cells are so small you can't see them without magnification! These special cells detect chemicals in the air and vibrations, sending messages to the grasshopper's brain. This is how the grasshopper \"smells\" food from far away and \"feels\" danger approaching. Even though we can see the antennae with our eyes, the actual sensing happens at the cellular level through chemical and electrical signals that travel through the grasshopper's nervous system.\n\n**Zoom Out: Ecosystem & Food Web Level**\nWhen we zoom out and look at the bigger picture, we see that this grasshopper is part of a whole community of living things. The grasshopper eats grass and leaves from plants. Birds, snakes, and lizards eat grasshoppers. When the grasshopper dies, decomposers break it down and return nutrients to the soil, helping plants grow. This creates a circular food web. The grasshopper on this leaf is connected to farmers (who worry about grasshoppers eating crops), to predators that depend on grasshoppers for food, and to the health of the entire ecosystem. Changes to one part of this system affect all the others.\n\n## 🤔 Potential Student Misconceptions\n\n**Misconception 1: \"Grasshoppers are insects, but they're also sometimes called bugs, so bugs and insects are the same thing.\"**\n*Scientific Clarification:* While people sometimes use the words \"bug\" and \"insect\" interchangeably in everyday language, scientists use \"insect\" as the specific scientific term. All insects have six legs, three body parts, and antennae. Not all bugs are insects (true bugs are a specific group that includes cicadas and water striders). It's helpful to teach students that \"insect\" is the correct scientific word, and they should use it when describing grasshoppers in science class.\n\n**Misconception 2: \"Grasshoppers are born as tiny grasshoppers and just grow bigger.\"**\n*Scientific Clarification:* Grasshoppers go through a life cycle with distinct stages. A grasshopper starts as an egg, hatches into a nymph (a young grasshopper that looks similar to an adult but is smaller and doesn't have wings), and molts (sheds its skin) several times as it grows. Eventually, it becomes an adult grasshopper with fully developed wings. This is different from insects like butterflies that go through metamorphosis (complete body transformation from caterpillar to butterfly).\n\n**Misconception 3: \"The grasshopper's green color was chosen by the grasshopper to hide.\"**\n*Scientific Clarification:* The grasshopper didn't decide to be green or choose this color for camouflage. Instead, over many generations, grasshoppers with green coloring survived better on green plants because predators couldn't see them as easily. Those grasshoppers lived longer, had more babies, and passed on the green color trait. This is **natural selection**—it's not a choice; it's something that happens over time.\n\n## 🔗 Cross-Curricular Ideas\n\n**Math Connection: Measuring Jumping Ability**\nHave students measure how far a grasshopper can jump compared to a human. If a grasshopper can jump 20 times its body length and a grasshopper is 2 inches long, how far is that? Then calculate: If a fourth grader is 50 inches tall and could jump proportionally as far as a grasshopper, how far would they jump? Create a class data table and graph showing different insects' jumping abilities. This reinforces multiplication, measurement, and data representation skills while deepening understanding of grasshopper adaptations.\n\n**ELA Connection: Descriptive Writing & Sequencing**\nHave students write a detailed paragraph describing what the grasshopper \"sees,\" \"feels,\" and \"experiences\" using sensory language. Students can write from the grasshopper's perspective: \"I sense movement through my antennae...\" This builds vocabulary, perspective-taking, and descriptive writing skills. Additionally, students can sequence the grasshopper's life cycle into a narrative with illustrations, practicing both writing and retelling skills.\n\n**Art Connection: Camouflage & Adaptation Art Project**\nStudents can create an artwork showing a grasshopper in its natural habitat (grass and leaves) and then redesign the grasshopper for a different habitat (desert, snow, forest floor). Using colored pencils, markers, or collage materials, they illustrate how the grasshopper's color and pattern would need to change to blend in with that new environment. This combines art skills with scientific thinking about structure, function, and adaptation.\n\n**Social Studies Connection: Human Impact on Habitats**\nDiscuss how grasshoppers' habitats (fields, grasslands, gardens) are affected by human activities like farming, building houses, and pesticide use. Students can research how farmers manage grasshopper populations or how we can create gardens that support grasshoppers and other insects. This connects to citizenship, environmental stewardship, and understanding how human decisions affect animal populations and ecosystems.\n\n## 🚀 STEM Career Connection\n\n**Entomologist (Insect Scientist)**\nAn entomologist is a scientist who studies insects like grasshoppers. Entomologists might observe grasshoppers in nature, learn about their life cycles, or study how they adapt to different environments. Some entomologists work to help farmers protect crops from grasshoppers, while others study how insects help ecosystems stay healthy. They use magnifying glasses, microscopes, and field notebooks to collect and understand data about insects. This job requires curiosity about nature and careful observation skills. **Average Annual Salary: $65,000–$75,000**\n\n**Agricultural Extension Agent**\nAn agricultural extension agent helps farmers solve problems with their crops and animals. If grasshoppers are eating too many crops, an extension agent gives farmers advice on how to manage grasshopper populations in ways that protect the environment. They might recommend when to plant crops to avoid grasshopper damage or suggest natural pest control methods. This job combines science knowledge with helping people in the community. **Average Annual Salary: $50,000–$65,000**\n\n**Wildlife Biologist**\nA wildlife biologist studies animals like grasshoppers and how they live in their habitats. They investigate questions like: \"What do grasshoppers need to survive?\" and \"How do changes in the environment affect grasshopper populations?\" Wildlife biologists might work in parks, nature reserves, or universities. They help protect animal populations and the habitats they depend on. **Average Annual Salary: $65,000–$78,000**\n\n## 📚 External Resources\n\n**Children's Books:**\n* *Grasshoppers* by Gail Gibbons (Clear illustrations and age-appropriate facts about grasshopper life cycles and behavior)\n* *The Very Hungry Caterpillar* by Eric Carle (Classic book connecting to insect growth and eating habits; can extend to discuss insect metamorphosis)\n* *Jump, Frog, Jump!* by Robert Kalan (Interactive rhyming text about jumping, connects to grasshopper adaptations)\n---\n\n**Teacher Tip:** This image is an excellent \"hook\" for a unit on animal structures and adaptations. Consider starting your lesson by asking students to predict what each body part does *before* revealing the answer. This activates their prior knowledge and makes the learning more engaging!",
  "generatedAt": "2026-02-06T22:43:51.464Z"
}